clixmlcreds/Export-CredentialToClixml.ps1
clixmlcreds/__init__.py
clixmlcreds/credentials.py
clixmlcreds/errors.py
clixmlcreds/utils.py
clixmlcreds-1.0.post1.dist-info/LICENSE
clixmlcreds-1.0.post1.dist-info/METADATA
clixmlcreds-1.0.post1.dist-info/WHEEL
clixmlcreds-1.0.post1.dist-info/top_level.txt
clixmlcreds-1.0.post1.dist-info/RECORD
