Metadata-Version: 2.1
Name: clixmlcreds
Version: 1.0.post1
Summary: Call Windows prompt for credentials with Python through PowerShell command Get-Credential.
Author-email: Anisimov Vladislav <pan.vlados.w@gmail.com>
License: MIT License
Project-URL: repository, https://github.com/pan-vlados/clixmlcreds
Keywords: WDPAPI,Export-Clixml,Get-Credential,PSCredential,clixml,credential,Windows,Protection
Classifier: Programming Language :: Python :: 3
Classifier: License :: OSI Approved :: MIT License
Classifier: Operating System :: Microsoft :: Windows
Classifier: Topic :: Security
Requires-Python: >=3.8.5
License-File: LICENSE
Requires-Dist: pywin32
Provides-Extra: dev
Requires-Dist: ruff ; extra == 'dev'
Requires-Dist: mypy ; extra == 'dev'
